my_unique_ml_package/__init__.py
my_unique_ml_package/decision_tree.py
my_unique_ml_package/data/UniversalBank.csv
my_unique_ml_package-0.3.dist-info/METADATA
my_unique_ml_package-0.3.dist-info/WHEEL
my_unique_ml_package-0.3.dist-info/entry_points.txt
my_unique_ml_package-0.3.dist-info/top_level.txt
my_unique_ml_package-0.3.dist-info/RECORD
