Metadata-Version: 2.1
Name: my_unique_ml_package
Version: 0.3
Summary: A simple machine learning package for decision tree classification
Home-page: https://github.com/yourusername/my_unique_ml_package
Author: Your Name
Author-email: your.email@example.com
Classifier: Programming Language :: Python :: 3
Classifier: License :: OSI Approved :: MIT License
Classifier: Operating System :: OS Independent
Requires-Python: >=3.6
Requires-Dist: pandas
Requires-Dist: scikit-learn
Requires-Dist: matplotlib
